hexastore/__init__.py
hexastore/hexastore.py
hexastore/version.py
hexastore-0.1.0.dist-info/LICENSE
hexastore-0.1.0.dist-info/METADATA
hexastore-0.1.0.dist-info/WHEEL
hexastore-0.1.0.dist-info/top_level.txt
hexastore-0.1.0.dist-info/RECORD
