Metadata-Version: 2.1
Name: hexastore
Version: 0.1.0
Summary: another hexastore implementation
Home-page: https://github.com/e-k-m/hexastore
Author: Eric Matti
License: UNKNOWN
Keywords: hexastore
Platform: UNKNOWN
Classifier: Development Status :: 3 - Alpha
Classifier: Intended Audience :: Developers
Classifier: Natural Language :: English
Classifier: Programming Language :: Python :: 3
Classifier: Programming Language :: Python :: 3.6
Classifier: Programming Language :: Python :: 3.7
Classifier: Programming Language :: Python :: 3.8
Classifier: Programming Language :: Python :: 3.9
Requires-Python: >=3.6
